ranimate/__init__.py
ranimate/__main__.py
ranimate/core.py
ranimate-0.1.2.dist-info/licenses/LICENCE
ranimate-0.1.2.dist-info/METADATA
ranimate-0.1.2.dist-info/WHEEL
ranimate-0.1.2.dist-info/entry_points.txt
ranimate-0.1.2.dist-info/top_level.txt
ranimate-0.1.2.dist-info/RECORD
