Metadata-Version: 2.4
Name: ranimate
Version: 0.1.2
Summary: Animation Library
Home-page: https://github.com/repaa818/ranimate
Author: Repaa
Author-email: personal@repaa.xyz
Requires-Python: >=3.10
License-File: LICENCE
Requires-Dist: pygame
Requires-Dist: numpy
Requires-Dist: opencv-python
Requires-Dist: moviepy
Requires-Dist: decorator
Requires-Dist: proglog
Requires-Dist: imageio
Requires-Dist: imageio-ffmpeg
Dynamic: author
Dynamic: author-email
Dynamic: description-content-type
Dynamic: home-page
Dynamic: license-file
Dynamic: requires-dist
Dynamic: requires-python
Dynamic: summary
